__init__.py
bible_search_engine/__init__.py
bible_search_engine/document_preprocessor.py
bible_search_engine/indexing.py
bible_search_engine/l2r.py
bible_search_engine/pipeline.py
bible_search_engine/preprocess_bible_data.py
bible_search_engine/ranker.py
bible_search_engine/relevance.py
bible_search_engine_ronenh24-0.0.3.dist-info/LICENSE
bible_search_engine_ronenh24-0.0.3.dist-info/METADATA
bible_search_engine_ronenh24-0.0.3.dist-info/WHEEL
bible_search_engine_ronenh24-0.0.3.dist-info/top_level.txt
bible_search_engine_ronenh24-0.0.3.dist-info/RECORD
