Metadata-Version: 2.2
Name: bible_search_engine_ronenh24
Version: 0.0.3
Summary: Bible search engine incorporating natural language processing, deep learning, and machine learning.
Author-email: Ronen H <ronenhuang24@gmail.com>
Project-URL: Homepage, https://github.com/ronenh24/bible_search_engine
Project-URL: Issues, https://github.com/ronenh24/bible_search_engine/issues
Classifier: Programming Language :: Python :: 3
Classifier: Operating System :: OS Independent
Classifier: License :: OSI Approved :: MIT License
Requires-Python: >=3.8
License-File: LICENSE
